.testr.conf
AUTHORS
ChangeLog
README.rst
requirements.txt
setup.cfg
setup.py
test-requirements.txt
tox.ini
fortiosclient/__init__.py
fortiosclient/_i18n.py
fortiosclient/base.py
fortiosclient/client.py
fortiosclient/eventlet_client.py
fortiosclient/eventlet_request.py
fortiosclient/exception.py
fortiosclient/request.py
fortiosclient/templates.py
fortiosclient.egg-info/PKG-INFO
fortiosclient.egg-info/SOURCES.txt
fortiosclient.egg-info/dependency_links.txt
fortiosclient.egg-info/not-zip-safe
fortiosclient.egg-info/pbr.json
fortiosclient.egg-info/requires.txt
fortiosclient.egg-info/top_level.txt
fortiosclient/common/__init__.py
fortiosclient/common/constants.py
fortiosclient/common/singleton.py
fortiosclient/tests/__init__.py
fortiosclient/tests/functional/__init__.py
fortiosclient/tests/functional/api_client/__init__.py
fortiosclient/tests/functional/api_client/test_templates.py
fortiosclient/tests/unit/__init__.py
fortiosclient/tests/unit/api_client/__init__.py
fortiosclient/tests/unit/api_client/test_api_eventlet_request.py
fortiosclient/tests/unit/api_client/test_client.py
tools/pretty_tox.sh
tools/subunit-trace.py
tools/tox_install.sh