Metadata-Version: 1.1
Name: fortiosclient
Version: 0.0.3
Summary: a python client based on fortios restful api
Home-page: http://www.fortinet.com
Author: Fortinet
Author-email: openstack-ci@fortinet.com
License: UNKNOWN
Platform: UNKNOWN
Classifier: Intended Audience :: Information Technology
Classifier: Intended Audience :: System Administrators
Classifier: License :: OSI Approved :: Apache Software License
Classifier: Operating System :: POSIX :: Linux
Classifier: Programming Language :: Python
Classifier: Programming Language :: Python :: 2
Classifier: Programming Language :: Python :: 2.7
Classifier: Programming Language :: Python :: 2.6
